deepkingnet/__init__.py
deepkingnet/help.py
deepkingnet/main.py
deepkingnet/data/100bp.model.h5
deepkingnet/data/10kb.model.h5
deepkingnet/data/1kb.model.h5
deepkingnet/data/200bp.model.h5
deepkingnet/data/2kb.model.h5
deepkingnet/data/300bp.model.h5
deepkingnet/data/3kb.model.h5
deepkingnet/data/4kb.model.h5
deepkingnet/data/500bp.model.h5
deepkingnet/data/5kb.model.h5
deepkingnet-0.0.1.dev0.dist-info/LICENSE.txt
deepkingnet-0.0.1.dev0.dist-info/METADATA
deepkingnet-0.0.1.dev0.dist-info/WHEEL
deepkingnet-0.0.1.dev0.dist-info/entry_points.txt
deepkingnet-0.0.1.dev0.dist-info/top_level.txt
deepkingnet-0.0.1.dev0.dist-info/RECORD
